pgtrun.py
pgturbo/__init__.py
pgturbo/__main__.py
pgturbo/_version.py
pgturbo/actor.py
pgturbo/animation.py
pgturbo/builtins.py
pgturbo/clock.py
pgturbo/constants.py
pgturbo/game.py
pgturbo/joystick.py
pgturbo/keyboard.py
pgturbo/loaders.py
pgturbo/mouse.py
pgturbo/music.py
pgturbo/ptext.py
pgturbo/rect.py
pgturbo/runner.py
pgturbo/screen.py
pgturbo/soundfmt.py
pgturbo/spellcheck.py
pgturbo/storage.py
pgturbo/tone.py
pgturbo/data/controllers_linux.txt
pgturbo/data/controllers_macos.txt
pgturbo/data/controllers_windows.txt
pgturbo/data/icon.png
pgturbo/data/joypad.png
pgturbo-1.3.7.dist-info/licenses/AUTHORS
pgturbo-1.3.7.dist-info/licenses/COPYING
pgturbo-1.3.7.dist-info/METADATA
pgturbo-1.3.7.dist-info/WHEEL
pgturbo-1.3.7.dist-info/entry_points.txt
pgturbo-1.3.7.dist-info/top_level.txt
pgturbo-1.3.7.dist-info/RECORD
