Metadata-Version: 2.4
Name: pgturbo
Version: 1.3.7
Summary: A fast moving zero-boilerplate 2D games framework
Project-URL: Documentation, https://pgturbo.readthedocs.io/
Project-URL: Source, https://github.com/Mambouna/pgturbo
Requires-Python: >=3.6
License-File: COPYING
License-File: AUTHORS
Requires-Dist: pygame>=2.1
Requires-Dist: numpy
Requires-Dist: pyfxr
Dynamic: license-file
